fds/__init__.py
fds/sdk/__init__.py
fds/sdk/QuantEngine/__init__.py
fds/sdk/QuantEngine/api_client.py
fds/sdk/QuantEngine/configuration.py
fds/sdk/QuantEngine/exceptions.py
fds/sdk/QuantEngine/model_utils.py
fds/sdk/QuantEngine/rest.py
fds/sdk/QuantEngine/api/__init__.py
fds/sdk/QuantEngine/api/quant_calculations_api.py
fds/sdk/QuantEngine/apis/__init__.py
fds/sdk/QuantEngine/model/__init__.py
fds/sdk/QuantEngine/model/calculation_status.py
fds/sdk/QuantEngine/model/calculation_status_meta.py
fds/sdk/QuantEngine/model/calculation_status_root.py
fds/sdk/QuantEngine/model/calculation_unit_status.py
fds/sdk/QuantEngine/model/calculation_unit_status_meta.py
fds/sdk/QuantEngine/model/calculations_summary.py
fds/sdk/QuantEngine/model/calculations_summary_root.py
fds/sdk/QuantEngine/model/client_error_response.py
fds/sdk/QuantEngine/model/error.py
fds/sdk/QuantEngine/model/error_source.py
fds/sdk/QuantEngine/model/object_root.py
fds/sdk/QuantEngine/model/one_of_quant_dates.py
fds/sdk/QuantEngine/model/one_of_quant_formulas.py
fds/sdk/QuantEngine/model/one_of_quant_formulas_array.py
fds/sdk/QuantEngine/model/one_of_quant_universe.py
fds/sdk/QuantEngine/model/pagination_info.py
fds/sdk/QuantEngine/model/pagination_meta.py
fds/sdk/QuantEngine/model/quant_all_universal_screen_parameters.py
fds/sdk/QuantEngine/model/quant_calculation_meta.py
fds/sdk/QuantEngine/model/quant_calculation_parameters.py
fds/sdk/QuantEngine/model/quant_calculation_parameters_root.py
fds/sdk/QuantEngine/model/quant_date.py
fds/sdk/QuantEngine/model/quant_date_list.py
fds/sdk/QuantEngine/model/quant_fds_date.py
fds/sdk/QuantEngine/model/quant_formula.py
fds/sdk/QuantEngine/model/quant_fql_expression.py
fds/sdk/QuantEngine/model/quant_identifier_universe.py
fds/sdk/QuantEngine/model/quant_screening_expression.py
fds/sdk/QuantEngine/model/quant_screening_expression_universe.py
fds/sdk/QuantEngine/model/quant_universal_screen_parameter.py
fds/sdk/QuantEngine/model/quant_universal_screen_universe.py
fds.sdk.QuantEngine-1.1.1.dist-info/LICENSE
fds.sdk.QuantEngine-1.1.1.dist-info/METADATA
fds.sdk.QuantEngine-1.1.1.dist-info/WHEEL
fds.sdk.QuantEngine-1.1.1.dist-info/top_level.txt
fds.sdk.QuantEngine-1.1.1.dist-info/RECORD
